{
    "1stlineAddress":  "ਪਹਿਲੀ ਲਾਈਨ ਪਤਾ",
    "2ndlineAddress":  "ਦੂਜੀ ਲਾਈਨ ਦਾ ਪਤਾ",
    "3rdlineAddress":  "3 ਪੰਗਤੀ ਪਤਾ",
    "4thLineAddress":  "ਚੌਥੀ ਲਾਈਨ ਦਾ ਪਤਾ",
    "AccountLockedpleaseresetPassword":  "ਖਾਤਾ ਬੰਦ ਹੈ ਕਿਰਪਾ ਕਰਕੇ ਪਾਸਵਰਡ ਰੀਸੈਟ ਕਰੋ",
    "Add":  "ਸ਼ਾਮਲ ਕਰੋ",
    "AddProducts":  "ਉਤਪਾਦ ਸ਼ਾਮਲ ਕਰੋ",
    "Afrikaans":  "ਅਫ਼ਰੀਕਨ",
    "Age":  "ਉਮਰ",
    "Alert":  "ਚੇਤਾਵਨੀ",
    "American":  "ਅਮਰੀਕੀ",
    "Amshoppingat":  "ਵਿਖੇ ਖਰੀਦਦਾਰੀ ਕਰ ਰਿਹਾ ਹਾਂ",
    "Anonymous":  "ਅਗਿਆਤ",
    "App":  "ਐਪ",
    "Arabic":  "ਅਰਬੀ",
    "Areyousureyouwanttodelete":  "ਕੀ ਤੁਸੀਂ ਪੱਕਾ ਮਿਟਾਉਣਾ ਚਾਹੁੰਦੇ ਹੋ?",
    "Areyousureyouwanttodeleteyourshopandallitscontents":  "ਕੀ ਤੁਹਾਨੂੰ ਪੱਕਾ ਯਕੀਨ ਹੈ ਕਿ ਤੁਸੀਂ ਆਪਣੀ ਦੁਕਾਨ ਅਤੇ ਇਸਦੀ ਸਾਰੀ ਸਮੱਗਰੀ ਨੂੰ ਮਿਟਾਉਣਾ ਚਾਹੁੰਦੇ ਹੋ",
    "Areyousureyouwanttodeleteyouruserprofileandallitscontents":  "ਕੀ ਤੁਹਾਨੂੰ ਯਕੀਨ ਹੈ ਕਿ ਤੁਸੀਂ ਆਪਣਾ ਉਪਭੋਗਤਾ ਪ੍ਰੋਫਾਈਲ ਅਤੇ ਇਸਦੀ ਸਾਰੀ ਸਮੱਗਰੀ ਨੂੰ ਮਿਟਾਉਣਾ ਚਾਹੁੰਦੇ ਹੋ?",
    "AreyousureyouwanttoupdateyourcurrentcompanyGPSfrom":  "ਕੀ ਤੁਹਾਨੂੰ ਯਕੀਨ ਹੈ ਕਿ ਤੁਸੀਂ ਆਪਣੀ ਮੌਜੂਦਾ ਕੰਪਨੀ GPS ਨੂੰ ਅਪਡੇਟ ਕਰਨਾ ਚਾਹੁੰਦੇ ਹੋ",
    "Australian":  "ਆਸਟਰੇਲੀਆਈ",
    "Back":  "ਵਾਪਸ",
    "BarcodeGenerator":  "ਕਿ Qਆਰ ਕੋਡ ਜੇਨਰੇਟਰ",
    "Basket":  "ਟੋਕਰੀ",
    "BlackBackGround":  "ਹਨੇਰ",
    "BlueBackGround":  "ਨੀਲਾ",
    "BreakfastIcon":  "ਨਾਸ਼ਤੇ ਦਾ ਆਈਕਨ",
    "BtnPasswordReset":  "ਪਾਸਵਰਡ ਰੀਸੈੱਟ",
    "BtnSignUp":  "ਭੁਗਤਾਨ ਗੇਟਵੇ ਤੇ ਸਾਈਨ ਅਪ ਕਰੋ",
    "Build":  "ਬਿਲਡ ਸ਼ਾਪ",
    "buttonModeBTN":  "ਬਟਨ ਮੋਡ",
    "buttonModeHold":  "ਹੋਲਡ ਮੋਡ",
    "buttonModeRightClick":  "ਸੱਜਾ ਕਲਿਕ ਮੋਡ",
    "buttonModeSwipe":  "ਸਵਾਈਪ ਮੋਡ",
    "CafeIcon":  "ਕੈਫੇ ਆਈਕਨ",
    "call":  "ਫੋਨ",
    "Camera":  "ਕੈਮਰਾ",
    "Cancel":  "ਰੱਦ ਕਰੋ",
    "Cannotcontinuetryagain":  "ਜਾਰੀ ਨਹੀਂ ਰਹਿ ਸਕਦਾ, ਦੁਬਾਰਾ ਕੋਸ਼ਿਸ਼ ਕਰੋ.",
    "Catalan":  "ਕੈਟਲਨ",
    "Chinesesimplified":  "ਚੀਨੀ (ਸਰਲ)",
    "ChineseTraditional":  "ਚੀਨੀ (ਰਵਾਇਤੀ)",
    "ChooseaMapMarker":  "ਇੱਕ ਨਕਸ਼ਾ ਮਾਰਕਰ ਚੁਣੋ",
    "Clear":  "ਸਾਫ",
    "Clickformoreinfo":  "ਵਧੇਰੇ ਜਾਣਕਾਰੀ ਲਈ ਕਲਿੱਕ ਕਰੋ",
    "ClickPintoaddCompany":  "ਕੰਪਨੀ ਨੂੰ ਜੋੜਨ ਲਈ ਪਿੰਨ ਤੇ ਕਲਿਕ ਕਰੋ",
    "ClosingTimes":  "ਸਮਾਪਤੀ ਦਾ ਸਮਾਂ",
    "ComingSoon":  "ਇਹ ਵਿਸ਼ੇਸ਼ਤਾ ਜਲਦੀ ਆ ਰਹੀ ਹੈ",
    "CompanyDescription":  "ਕੰਪਨੀ ਵੇਰਵਾ",
    "CompanyEmail":  "ਕੰਪਨੀ ਈ",
    "CompanyMenuDetailsPageTitle":  "ਸੋਧ ਮੇਨੂ ਆਈਟਮ ਵੇਰਵੇ ਸ਼ਾਮਲ ਕਰੋ",
    "CompanyMenuGroupPageTitle":  "ਸੋਧ ਮੇਨੂ ਸਮੂਹ ਸ਼ਾਮਲ ਕਰੋ",
    "CompanyName":  "ਕੰਪਨੀ ਦਾ ਨਾਂ",
    "CompanyProfile":  "ਕੰਪਨੀ ਪ੍ਰੋਫਾਇਲ",
    "CompanyProfilePageTitle":  "ਕੰਪਨੀ ਪ੍ਰੋਫਾਈਲ ਸੋਧੋ",
    "CompanyReadonlyDetails":  "ਡਿਜੀਟਲ ਸ਼ਾਪ ਗ੍ਰਾਹਕ ਨੂੰ ਡਿਜੀਟਲ ਸ਼ਾਪ ਉਦਮੀ ਬਾਰੇ ਕੋਈ relevantੁਕਵੀਂ ਜਾਣਕਾਰੀ ਵੇਖਣ ਦੇ ਯੋਗ ਹੋਣਾ ਚਾਹੀਦਾ ਹੈ ਤਾਂ ਕਿ ਜੇਕਰ ਉਨ੍ਹਾਂ ਨੂੰ ਆਰਡਰ ਨਾਲ ਕੋਈ ਮੁੱਦਾ ਹੋਇਆ ਤਾਂ ਉਨ੍ਹਾਂ ਨਾਲ ਸੰਪਰਕ ਕਰੋ.",
    "CompanyRegisterPageTitle":  "ਕੰਪਨੀ ਰਜਿਸਟਰ",
    "Country":  "ਦੇਸ਼",
    "Currentordersdependingonthisitempleasedeletefirstinyourcompnyorders":  "ਇਸ ਆਈਟਮ ਦੇ ਅਧਾਰ ਤੇ ਮੌਜੂਦਾ ਆਰਡਰ, ਕਿਰਪਾ ਕਰਕੇ ਆਪਣੀ ਕੰਪਨੀ ਦੇ ਆਰਡਰ ਵਿੱਚ ਪਹਿਲਾਂ ਮਿਟਾਓ",
    "CustomerReadonlyDetails":  "ਡਿਜੀਟਲ ਸ਼ਾਪ ਉਦਯੋਗਪਤੀ ਨੂੰ ਹੁਣ ਡਿਜੀਟਲ ਸ਼ਾਪ ਗਾਹਕ ਬਾਰੇ ਕੋਈ ਵੀ ਜਾਣਕਾਰੀ ਵੇਖਣ ਦੇ ਯੋਗ ਹੋਣਾ ਚਾਹੀਦਾ ਹੈ ਤਾਂ ਜੋ ਉਨ੍ਹਾਂ ਨੂੰ ਉਤਪਾਦਾਂ ਨੂੰ ਪਹੁੰਚਾ ਸਕਣ.",
    "Danish":  "ਡੈਨਿਸ਼",
    "Daysago":  "ਦਿਨ ਪਹਿਲਾਂ",
    "Delete":  "ਮਿਟਾਓ",
    "DeleteContextAction":  "ਪ੍ਰਸੰਗਿਕ ਕਾਰਵਾਈ ਨੂੰ ਮਿਟਾਓ",
    "DELETEYOURPROFILE":  "ਆਪਣੀ ਪ੍ਰੋਫਾਈਲ ਹਟਾਓ",
    "DELETEYOURSHOP":  "ਆਪਣੀ ਦੁਕਾਨ ਹਟਾਓ",
    "Deliver":  "ਸਪੁਰਦ ਕਰੋ",
    "Delivered":  "ਦਿੱਤਾ ਗਿਆ",
    "DeliveriesareEnabled":  "ਸਪੁਰਦਗੀ ਯੋਗ ਹੈ",
    "DeliveryNotes":  "ਡਿਲਿਵਰੀ ਨੋਟਸ",
    "DeliveryStatus":  "ਡਿਲਿਵਰੀ ਸਥਿਤੀ",
    "DeliveryType":  "ਡਿਲਿਵਰੀ ਦੀ ਕਿਸਮ",
    "DetaileswerenotSaved":  "ਵੇਰਵੇ ਸੇਵ ਨਹੀਂ ਕੀਤੇ ਗਏ ਸਨ",
    "DetailswereSaved":  "ਵੇਰਵੇ ਸੁਰੱਖਿਅਤ ਕੀਤੇ ਗਏ ਸਨ",
    "Dutch":  "ਡੱਚ",
    "Edit":  "ਸੰਪਾਦਿਤ ਕਰੋ",
    "Email":  "ਈ - ਮੇਲ",
    "EmailAddress":  "ਈਮੇਲ ਖਾਤਾ",
    "EnableNotifications":  "ਸੂਚਨਾਵਾਂ ਨੂੰ ਸਮਰੱਥ ਕਰੋ",
    "EnabletoAllowDeliveries":  "ਸਪੁਰਦਗੀ ਦੀ ਆਗਿਆ ਦੇ ਯੋਗ ਕਰੋ",
    "EnableToAllowGlobal":  "ਗਲੋਬਲ ਦੀ ਇਜਾਜ਼ਤ ਦੇਣ ਲਈ ਸਮਰੱਥ ਬਣਾਓ",
    "EnabletoAllowPayOnPhone":  "ਫੋਨ ਤੇ ਭੁਗਤਾਨ ਦੀ ਆਗਿਆ ਦੇ ਯੋਗ ਕਰੋ",
    "EnabletoAllowTakeaways":  "ਟੇਕਵੇਅ ਦੀ ਆਗਿਆ ਦੇ ਯੋਗ ਕਰੋ",
    "Enabletodisplay":  "ਪ੍ਰਦਰਸ਼ਤ ਕਰਨ ਦੇ ਯੋਗ",
    "EnabletoRecieveOrders":  "ਆਰਡਰ ਪ੍ਰਾਪਤ ਕਰਨ ਦੇ ਯੋਗ",
    "English":  "ਅੰਗਰੇਜ਼ੀ",
    "EnterShop":  "ਦੁਕਾਨ ਦਿਓ",
    "Errorwithaccountpleasetryresettingpasswordorcontactingsupport":  "ਖਾਤੇ ਨਾਲ ਗਲਤੀ, ਕਿਰਪਾ ਕਰਕੇ ਪਾਸਵਰਡ ਰੀਸੈਟ ਕਰਨ ਜਾਂ ਸਹਾਇਤਾ ਨਾਲ ਸੰਪਰਕ ਕਰਨ ਦੀ ਕੋਸ਼ਿਸ਼ ਕਰੋ. ",
    "ErrorwithPrice":  "ਕੀਮਤ ਨਾਲ ਗਲਤੀ ਕਿਰਪਾ ਕਰਕੇ 0.00 ਜਾਂ 0 ਵਰਗੀ ਕੋਸ਼ਿਸ਼ ਕਰੋ",
    "Ethiopian":  "ਈਥੋਪੀਅਨ",
    "Female":  "Femaleਰਤ",
    "Finnish":  "ਫਿਨਿਸ਼",
    "FirstName":  "ਪਹਿਲਾ ਨਾਂ",
    "FreeView":  "ਮੁਫਤ ਦੁਕਾਨਾਂ ਵੇਖੋ",
    "French":  "ਫ੍ਰੈਂਚ",
    "Gallery":  "ਗੈਲਰੀ",
    "Gender":  "ਲਿੰਗ",
    "German":  "ਜਰਮਨ",
    "GlobalEnabled":  "ਗਲੋਬਲ ਸਮਰਥਿਤ ਹੈ",
    "goingtoneedthatlocation":  "ਉਸ ਜਗ੍ਹਾ ਦੀ ਲੋੜ ਜਾ ਰਹੀ ਹੈ",
    "goingtoneedthatStorage":  "ਉਸ ਸਟੋਰੇਜ ਦੀ ਜ਼ਰੂਰਤ ਜਾ ਰਹੀ ਹੈ",
    "GoogleIcon":  "ਗੂਗਲ ਆਈਕਾਨ",
    "GoPro":  "ਅਪਗ੍ਰੇਡ ਕਰੋ",
    "Greek":  "ਯੂਨਾਨੀ",
    "GroupName":  "ਸਮੂਹ ਦਾ ਨਾਮ",
    "Groups":  "ਸਮੂਹ",
    "Hebrew":  "ਇਬਰਾਨੀ",
    "HELPBARCODE":  "ਜੇ ਡਿਜੀਟਲ ਸ਼ਾਪ ਉੱਦਮੀ ਨੇ ਤੁਹਾਨੂੰ ਆਪਣਾ ਡਿਜੀਟਲ ਸ਼ਾਪ ਕਿ Qਆਰ ਕੋਡ ਭੇਜਿਆ ਹੈ ਜਾਂ ਇਸ ਨੂੰ ਟੇਬਲ ਤੇ ਜਾਂ ਡਿਜੀਟਲ ਸ਼ਾਪ ਸਥਾਨ ਤੇ ਪ੍ਰਦਰਸ਼ਿਤ ਕੀਤਾ ਹੈ, ਤਾਂ ਤੁਸੀਂ ਇਸ ਸਕੈਨਰ ਦੀ ਵਰਤੋਂ ਵਿਲੱਖਣ ਕਿRਆਰ ਕੋਡ ਨੂੰ ਪੜ੍ਹਨ ਲਈ ਕਰ ਸਕਦੇ ਹੋ ਜੋ ਤੁਹਾਨੂੰ ਸਿੱਧੇ ਤੌਰ \u0027ਤੇ ਡਿਜੀਟਲ ਸ਼ਾਪ ਨਕਸ਼ੇ ਨੂੰ ਦੁਕਾਨ ਤੋਂ ਦੁਕਾਨ\u0027 ਤੇ ਲੈ ਜਾਵੇਗਾ. ",
    "HELPCOMPANYADDDETAILS":  "ਤਸਵੀਰ ਦੇ ਨਾਲ ਜਾਂ ਬਿਨਾਂ ਆਪਣੀ ਨਵੀਂ ਉਤਪਾਦ ਜਾਣਕਾਰੀ ਸ਼ਾਮਲ ਕਰੋ ਅਤੇ ਖ਼ਤਮ ਕਰਨ ਲਈ ਸੇਵ ਕਲਿੱਕ ਕਰੋ.",
    "HELPCOMPANYADDNAME":  "ਆਪਣੇ ਮੀਨੂ ਸਮੂਹ ਲਈ ਇੱਕ ਨਾਮ ਸ਼ਾਮਲ ਕਰੋ ਅਤੇ ਸੇਵ ਕਲਿੱਕ ਕਰੋ.",
    "HELPCOMPANYGROUPANDROID":  "ਆਪਣੀ ਡਿਜੀਟਲ ਸ਼ਾਪ ਕੰਪਨੀ ਵਿਚ ਇਕ ਨਵਾਂ ਸਮੂਹ ਜੋੜਨਾ, ਸੋਧਣਾ ਜਾਂ ਮਿਟਾਉਣ ਲਈ, ਉਸ ਸਮੂਹ ਨੂੰ ਫੜੀ ਰੱਖੋ ਜੋ ਤੁਸੀਂ ਬਣਾਇਆ ਹੈ ਅਤੇ ਸ਼ਾਮਲ ਕਰੋ, ਸੰਪਾਦਿਤ ਕਰੋ ਜਾਂ ਮਿਟਾਓ ਵਿਕਲਪਾਂ ਦੀ ਚੋਣ ਕਰੋ ਜਾਂ ਨਵਾਂ ਉਤਪਾਦ ਸ਼ਾਮਲ ਕਰਨ ਲਈ ਸਿਰਫ ਇਕ ਵਾਰ ਕਲਿੱਕ ਕਰੋ. ",
    "HELPCOMPANYGROUPIPHONE":  "ਆਪਣੀ ਡਿਜੀਟਲ ਸ਼ਾਪ ਕੰਪਨੀ ਵਿੱਚ ਇੱਕ ਨਵਾਂ ਸਮੂਹ ਸ਼ਾਮਲ ਕਰਨ, ਸੰਪਾਦਿਤ ਕਰਨ ਜਾਂ ਮਿਟਾਉਣ ਲਈ, ਜਿਸ ਸਮੂਹ ਨੂੰ ਤੁਸੀਂ ਬਣਾਇਆ ਹੈ ਉਸ ਉੱਤੇ ਖੱਬੇ ਪਾਸੇ ਛੱਡੋ ਅਤੇ ਸ਼ਾਮਲ ਕਰੋ, ਸੰਪਾਦਿਤ ਕਰੋ ਜਾਂ ਮਿਟਾਓ ਵਿਕਲਪਾਂ ਦੀ ਚੋਣ ਕਰੋ ਜਾਂ ਇੱਕ ਨਵਾਂ ਉਤਪਾਦ ਸ਼ਾਮਲ ਕਰਨ ਲਈ ਸਿਰਫ ਇੱਕ ਵਾਰ ਕਲਿੱਕ ਕਰੋ. ",
    "HELPCOMPANYGROUPNOPIC":  "ਆਪਣੀ ਡਿਜੀਟਲ ਸ਼ਾਪ ਕੰਪਨੀ ਵਿੱਚ ਇੱਕ ਨਵਾਂ ਸਮੂਹ ਜੋੜਨਾ, ਸੋਧਣਾ ਜਾਂ ਮਿਟਾਉਣ ਲਈ, ਉਸ ਸਮੂਹ ਉੱਤੇ ਕਲਿਕ ਕਰੋ ਜੋ ਤੁਸੀਂ ਬਣਾਇਆ ਹੈ ਅਤੇ ਸ਼ਾਮਲ ਕਰੋ, ਸੰਪਾਦਿਤ ਕਰੋ ਜਾਂ ਮਿਟਾਓ ਬਟਨ ਦੀ ਚੋਣ ਕਰੋ ਜਾਂ ਇੱਕ ਨਵਾਂ ਉਤਪਾਦ ਸ਼ਾਮਲ ਕਰਨ ਲਈ ਸਮੂਹ ਤੇ ਇੱਕ ਵਾਰ ਕਲਿੱਕ ਕਰੋ. ",
    "HELPCOMPANYGROUPWINDOWS10":  "ਆਪਣੀ ਡਿਜੀਟਲ ਸ਼ਾਪ ਕੰਪਨੀ ਵਿੱਚ ਇੱਕ ਨਵਾਂ ਸਮੂਹ ਜੋੜਨਾ, ਸੋਧਣਾ ਜਾਂ ਮਿਟਾਉਣ ਲਈ, ਉਸ ਸਮੂਹ ਉੱਤੇ ਸੱਜਾ ਕਲਿਕ ਕਰੋ ਜੋ ਤੁਸੀਂ ਬਣਾਇਆ ਹੈ ਅਤੇ ਸ਼ਾਮਲ ਕਰੋ, ਸੰਪਾਦਿਤ ਜਾਂ ਹਟਾਓ ਵਿਕਲਪਾਂ ਦੀ ਚੋਣ ਕਰੋ ਜਾਂ ਇੱਕ ਨਵਾਂ ਉਤਪਾਦ ਜੋੜਨ ਲਈ ਸਿਰਫ ਇੱਕ ਵਾਰ ਕਲਿੱਕ ਕਰੋ. ",
    "HELPCOMPANYPROFILE":  "ਇਹ ਡਿਜੀਟਲ ਸ਼ਾਪ ਕੰਪਨੀ ਪ੍ਰੋਫਾਈਲ ਹੈ ਜਿਥੇ ਤੁਸੀਂ ਆਪਣੀ ਕੰਪਨੀ ਤਸਵੀਰ ਨੂੰ ਸ਼ਾਮਲ ਕਰ ਸਕਦੇ ਹੋ ਅਤੇ ਜਿੰਨਾ ਹੋ ਸਕੇ ਅਨੁਕੂਲਿਤ ਕਰ ਸਕਦੇ ਹੋ. ",
    "HELPCOMPANYREGISTER":  "ਜਦੋਂ ਤੁਸੀਂ ਪਹਿਲੀ ਵਾਰ ਡਿਜੀਟਲ ਸ਼ਾਪ ਬਣਾਉਂਦੇ ਹੋ ਤਾਂ ਇਹ ਤੁਹਾਡੇ ਮੌਜੂਦਾ ਜੀਪੀਐਸ ਸਥਾਨ ਨੂੰ ਬਚਾਉਂਦਾ ਹੈ. ",
    "HELPEDITDETAILSFULL":  "ਤਸਵੀਰ ਦੇ ਨਾਲ ਜਾਂ ਬਿਨਾਂ ਆਪਣੀ ਨਵੀਂ ਉਤਪਾਦ ਜਾਣਕਾਰੀ ਨੂੰ ਸੋਧੋ ਅਤੇ ਮੁਕੰਮਲ ਕਰਨ ਲਈ ਸੇਵ ਕਲਿੱਕ ਕਰੋ.",
    "HELPEDITMENUDETAILSANDROID":  "ਆਪਣੀ ਡਿਜੀਟਲ ਸ਼ਾਪ ਕੰਪਨੀ ਵਿੱਚ ਇੱਕ ਨਵਾਂ ਉਤਪਾਦ ਸ਼ਾਮਲ ਕਰਨ, ਸੰਪਾਦਿਤ ਕਰਨ ਜਾਂ ਮਿਟਾਉਣ ਲਈ ਜੋ ਉਤਪਾਦ ਤੁਸੀਂ ਬਣਾਇਆ ਹੈ ਉਸਨੂੰ ਦਬਾ ਕੇ ਰੱਖੋ ਅਤੇ ਸ਼ਾਮਲ ਕਰੋ, ਸੋਧੋ ਜਾਂ ਮਿਟਾਓ ਵਿਕਲਪਾਂ ਦੀ ਚੋਣ ਕਰੋ ਜਾਂ ਇੱਕ ਵਾਰ ਸੰਪਾਦਿਤ ਕਰਨ ਲਈ ਕਲਿਕ ਕਰੋ. ",
    "HELPEDITMENUDETAILSIPHONE":  "ਆਪਣੀ ਡਿਜੀਟਲ ਸ਼ਾਪ ਕੰਪਨੀ ਵਿੱਚ ਇੱਕ ਨਵਾਂ ਉਤਪਾਦ ਸ਼ਾਮਲ ਕਰਨ, ਸੰਪਾਦਿਤ ਕਰਨ ਜਾਂ ਮਿਟਾਉਣ ਲਈ, ਤੁਸੀਂ ਜੋ ਉਤਪਾਦ ਬਣਾਇਆ ਹੈ ਉਸ ਤੇ ਖੱਬੇ ਪਾਸੇ ਛੱਡੋ ਅਤੇ ਸ਼ਾਮਲ ਕਰੋ, ਸੰਪਾਦਿਤ ਕਰੋ ਜਾਂ ਮਿਟਾਓ ਵਿਕਲਪਾਂ ਦੀ ਚੋਣ ਕਰੋ ਜਾਂ ਇੱਕ ਵਾਰ ਸੰਪਾਦਿਤ ਕਰਨ ਲਈ ਕਲਿਕ ਕਰੋ. ",
    "HELPEDITMENUDETAILSNOPIC":  "ਆਪਣੀ ਡਿਜੀਟਲ ਸ਼ਾਪ ਕੰਪਨੀ ਵਿੱਚ ਇੱਕ ਨਵਾਂ ਉਤਪਾਦ ਜੋੜਨਾ, ਸੋਧਣਾ ਜਾਂ ਮਿਟਾਉਣ ਲਈ, ਉਸ ਉਤਪਾਦ \u0027ਤੇ ਕਲਿਕ ਕਰੋ ਜੋ ਤੁਸੀਂ ਬਣਾਇਆ ਹੈ ਅਤੇ ਚੁਣੋ, ਸੰਪਾਦਨ ਜਾਂ ਮਿਟਾਓ ਬਟਨ ਚੁਣੋ ਜਾਂ ਸੰਪਾਦਿਤ ਕਰਨ ਲਈ ਇੱਕ ਵਾਰ ਕਲਿੱਕ ਕਰੋ. ",
    "HELPEDITMENUDETAILSWINDOWS10":  "ਆਪਣੀ ਡਿਜੀਟਲ ਸ਼ਾਪ ਕੰਪਨੀ ਵਿਚ ਇਕ ਨਵਾਂ ਉਤਪਾਦ ਸ਼ਾਮਲ ਕਰਨਾ, ਸੋਧਣਾ ਜਾਂ ਮਿਟਾਉਣ ਲਈ ਜੋ ਉਤਪਾਦ ਤੁਸੀਂ ਬਣਾਇਆ ਹੈ ਉਸ ਉੱਤੇ ਸੱਜਾ ਕਲਿਕ ਕਰੋ ਅਤੇ ਸ਼ਾਮਲ ਕਰੋ, ਸੰਪਾਦਿਤ ਕਰੋ ਜਾਂ ਮਿਟਾਓ ਵਿਕਲਪਾਂ ਦੀ ਚੋਣ ਕਰੋ ਜਾਂ ਇਕ ਵਾਰ ਸੰਪਾਦਿਤ ਕਰਨ ਲਈ ਕਲਿਕ ਕਰੋ. ",
    "HELPFRONTDOOR":  "ਡਿਜੀਟਲ ਦੁਕਾਨ ਦਾ ਗਾਹਕ ਹੁਣ ਦੁਕਾਨ \u0027ਤੇ ਜਾਣਕਾਰੀ ਦੇਖਦਾ ਹੈ ਜਿਸ ਨਾਲ ਉਹ ਗੱਲਬਾਤ ਕਰਨਾ ਚਾਹੁੰਦੇ ਹਨ. ",
    "HELPFRONTDOORGROUPS":  "ਤੁਹਾਨੂੰ ਹੁਣ ਇਸ ਮੌਜੂਦਾ ਡਿਜੀਟਲ ਦੁਕਾਨ ਲਈ ਪਬਲਿਕ ਮੀਨੂ ਸਿਸਟਮ ਤੇ ਸਮੂਹ ਵੇਖਣੇ ਚਾਹੀਦੇ ਹਨ. ",
    "HELPFRONTDOORPRODUCTS":  "ਜੇ ਡਿਜੀਟਲ ਸ਼ਾਪ ਉਦਮੀ ਨੇ ਆਪਣੇ ਉਤਪਾਦਾਂ ਨੂੰ ਕਿਰਿਆਸ਼ੀਲ ਬਣਾਇਆ ਹੈ, ਤਾਂ ਤੁਹਾਨੂੰ ਹੁਣ ਆੱਰਡਰ ਦੇਣ ਲਈ ਉਪਲਬਧ ਉਤਪਾਦਾਂ ਨੂੰ ਵੇਖਣਾ ਚਾਹੀਦਾ ਹੈ. ",
    "HelpInfomation":  "ਸਹਾਇਤਾ ਜਾਣਕਾਰੀ",
    "Helpisoff":  "ਮਦਦ ਬੰਦ",
    "Helpison":  "ਸਹਾਇਤਾ \u0027ਤੇ",
    "HELPLIVEORDERSWINDOWS10":  "ਇਹ ਸਕ੍ਰੀਨ ਡਿਜੀਟਲ ਸ਼ਾਪ ਉਦਯੋਗਪਤੀ ਨੂੰ ਕੋਈ ਕਿਰਿਆਸ਼ੀਲ ਆਰਡਰ ਦਰਸਾਉਂਦੀ ਹੈ ਜੋ ਉਹਨਾਂ ਕੋਲ ਇਸ ਸਮੇਂ ਹੋ ਸਕਦੀ ਹੈ ਅਤੇ ਇਹ ਸੈੱਟ ਕਰਨ ਦੇ ਯੋਗ ਹੈ ਜੇ ਆਰਡਰ ਭੁਗਤਾਨ ਕੀਤਾ ਜਾਂ ਦਿੱਤਾ ਗਿਆ ਹੈ. ",
    "HELPLIVEORSERSANDROID":  "ਇਹ ਸਕ੍ਰੀਨ ਡਿਜੀਟਲ ਸ਼ਾਪ ਉਦਯੋਗਪਤੀ ਨੂੰ ਕੋਈ ਕਿਰਿਆਸ਼ੀਲ ਆਰਡਰ ਦਰਸਾਉਂਦੀ ਹੈ ਜੋ ਉਹਨਾਂ ਕੋਲ ਇਸ ਸਮੇਂ ਹੋ ਸਕਦੀ ਹੈ ਅਤੇ ਇਹ ਸੈੱਟ ਕਰਨ ਦੇ ਯੋਗ ਹੈ ਜੇ ਆਰਡਰ ਭੁਗਤਾਨ ਕੀਤਾ ਜਾਂ ਦਿੱਤਾ ਗਿਆ ਹੈ. ",
    "HELPLIVEORSERSIPHONE":  "ਇਹ ਸਕ੍ਰੀਨ ਡਿਜੀਟਲ ਸ਼ਾਪ ਉਦਯੋਗਪਤੀ ਨੂੰ ਕੋਈ ਕਿਰਿਆਸ਼ੀਲ ਆਰਡਰ ਦਰਸਾਉਂਦੀ ਹੈ ਜੋ ਉਹਨਾਂ ਕੋਲ ਇਸ ਸਮੇਂ ਹੋ ਸਕਦੀ ਹੈ ਅਤੇ ਇਹ ਸੈੱਟ ਕਰਨ ਦੇ ਯੋਗ ਹੈ ਜੇ ਆਰਡਰ ਭੁਗਤਾਨ ਕੀਤਾ ਜਾਂ ਦਿੱਤਾ ਗਿਆ ਹੈ. ",
    "HELPLIVEORSERSNOPIC":  "ਇਹ ਸਕ੍ਰੀਨ ਡਿਜੀਟਲ ਸ਼ਾਪ ਉਦਯੋਗਪਤੀ ਨੂੰ ਕੋਈ ਕਿਰਿਆਸ਼ੀਲ ਆਰਡਰ ਦਰਸਾਉਂਦੀ ਹੈ ਜੋ ਉਹਨਾਂ ਕੋਲ ਇਸ ਸਮੇਂ ਹੋ ਸਕਦੀ ਹੈ ਅਤੇ ਇਹ ਸੈੱਟ ਕਰਨ ਦੇ ਯੋਗ ਹੈ ਜੇ ਆਰਡਰ ਭੁਗਤਾਨ ਕੀਤਾ ਜਾਂ ਦਿੱਤਾ ਗਿਆ ਹੈ. ",
    "HELPMAIN":  "ਡਿਜੀਟਲ ਦੁਕਾਨ ਇਕ ਅਜਿਹਾ ਐਪ ਹੈ ਜੋ ਤੁਹਾਨੂੰ ਤੁਹਾਡੀ ਮੌਜੂਦਾ ਜੀਪੀਐਸ ਸਥਿਤੀ \u0027ਤੇ ਉਸ ਡਿਜੀਟਲ ਸ਼ਾਪ ਵਿਚ ਉਤਪਾਦ ਬਣਾਉਣ, ਵਰਚੁਅਲ ਦੁਕਾਨ ਨੂੰ ਅਨੁਕੂਲਿਤ ਕਰਨ ਅਤੇ ਉਤਪਾਦਾਂ ਨੂੰ ਜੋੜਨ ਦੀ ਆਗਿਆ ਦੇਵੇਗਾ. ",
    "HELPMAPMANY":  "ਇਹ ਨਕਸ਼ਾ ਤੁਹਾਨੂੰ ਕੋਈ ਵੀ ਮੁਫਤ ਡਿਜੀਟਲ ਦੁਕਾਨਾਂ ਦਿਖਾਵੇਗਾ ਜੋ ਤੁਹਾਡੇ ਮੌਜੂਦਾ ਖੇਤਰ ਵਿੱਚ ਬਣਾਇਆ ਗਿਆ ਹੈ. ",
    "HELPMAPTOP":  "ਇਹ ਸਕ੍ਰੀਨ ਤੁਹਾਨੂੰ ਆਪਣੇ ਸਥਾਨਕ ਖੇਤਰ ਵਿਚ ਡਿਜੀਟਲ ਦੁਕਾਨ ਲੱਭਣ ਵਿਚ ਸਹਾਇਤਾ ਕਰਦੀ ਹੈ. ",
    "HELPORDERHISTORYANDROID":  "ਤੁਸੀਂ ਕੋਈ ਵੀ ਨਵਾਂ ਆਰਡਰ ਦੇਖ ਸਕਦੇ ਹੋ ਅਤੇ ਦੇਖ ਸਕਦੇ ਹੋ ਕਿ ਇਹ ਦਿੱਤਾ ਜਾਂ ਭੁਗਤਾਨ ਕੀਤਾ ਗਿਆ ਹੈ. ",
    "HELPORDERHISTORYIPHONE":  "ਤੁਸੀਂ ਕੋਈ ਵੀ ਨਵਾਂ ਆਰਡਰ ਦੇਖ ਸਕਦੇ ਹੋ ਅਤੇ ਦੇਖ ਸਕਦੇ ਹੋ ਕਿ ਇਹ ਦਿੱਤਾ ਜਾਂ ਭੁਗਤਾਨ ਕੀਤਾ ਗਿਆ ਹੈ. ",
    "HELPORDERHISTORYNOPIC":  "ਤੁਸੀਂ ਕੋਈ ਵੀ ਨਵਾਂ ਆਰਡਰ ਦੇਖ ਸਕਦੇ ਹੋ ਅਤੇ ਦੇਖ ਸਕਦੇ ਹੋ ਕਿ ਇਹ ਦਿੱਤਾ ਜਾਂ ਭੁਗਤਾਨ ਕੀਤਾ ਗਿਆ ਹੈ. ",
    "HELPORDERHISTORYWINDOWS10":  "ਤੁਸੀਂ ਕੋਈ ਵੀ ਨਵਾਂ ਆਰਡਰ ਦੇਖ ਸਕਦੇ ਹੋ ਅਤੇ ਦੇਖ ਸਕਦੇ ਹੋ ਕਿ ਇਹ ਦਿੱਤਾ ਜਾਂ ਭੁਗਤਾਨ ਕੀਤਾ ਗਿਆ ਹੈ. ",
    "HELPTOTALORDERSANDROID":  "ਕਿਰਪਾ ਕਰਕੇ ਆਪਣੇ ਆਰਡਰ ਨੂੰ ਸਕੈਨ ਕਰੋ ਅਤੇ ਜੇ ਕੋਈ ਅਜਿਹੀ ਚੀਜ਼ ਹੈ ਜਿਸਦੀ ਤੁਸੀਂ ਆਰਡਰ ਨਹੀਂ ਕਰਨਾ ਚਾਹੁੰਦੇ ਤਾਂ ਸਿਰਫ ਉਸ ਇਕਾਈ ਨੂੰ ਹੋਲਡ ਕਰੋ ਅਤੇ ਮਿਟਾਉਣ ਲਈ ਵਿਕਲਪ ਦੀ ਚੋਣ ਕਰੋ ਅਤੇ ਇਸ ਨੂੰ ਇਸਨੂੰ ਤੁਹਾਡੀ ਕੁੱਲ ਆਰਡਰ ਸੂਚੀ ਤੋਂ ਹਟਾ ਦੇਣਾ ਚਾਹੀਦਾ ਹੈ. ",
    "HELPTOTALORDERSIPHONE":  "ਕਿਰਪਾ ਕਰਕੇ ਆਪਣੇ ਆਰਡਰ ਨੂੰ ਸਕੈਨ ਕਰੋ ਅਤੇ ਜੇ ਕੋਈ ਅਜਿਹੀ ਚੀਜ਼ ਹੈ ਜੋ ਤੁਸੀਂ ਉਸ ਚੀਜ਼ \u0027ਤੇ ਖੱਬੇ ਪਾਸੇ ਸਵਾਈਪ ਨੂੰ ਆਰਡਰ ਨਹੀਂ ਕਰਨਾ ਚਾਹੁੰਦੇ ਹੋ ਅਤੇ ਮਿਟਾਉਣ ਲਈ ਵਿਕਲਪ ਦੀ ਚੋਣ ਕਰੋ ਅਤੇ ਇਸ ਨੂੰ ਇਸਨੂੰ ਤੁਹਾਡੀ ਕੁੱਲ ਆਰਡਰ ਸੂਚੀ ਤੋਂ ਹਟਾ ਦੇਣਾ ਚਾਹੀਦਾ ਹੈ. ",
    "HELPTOTALORDERSNOPIC":  "ਕਿਰਪਾ ਕਰਕੇ ਆਪਣੇ ਆਰਡਰ ਨੂੰ ਸਕੈਨ ਕਰੋ ਅਤੇ ਜੇ ਕੋਈ ਅਜਿਹੀ ਚੀਜ਼ ਹੈ ਜਿਸਦੀ ਤੁਸੀਂ ਆਰਡਰ ਨਹੀਂ ਕਰਨਾ ਚਾਹੁੰਦੇ ਤਾਂ ਉਸ ਆਈਟਮ ਦੇ ਬਟਨ ਨੂੰ ਕਲਿੱਕ ਕਰੋ ਅਤੇ ਮਿਟਾਉਣ ਲਈ ਵਿਕਲਪ ਦੀ ਚੋਣ ਕਰੋ ਅਤੇ ਇਸ ਨੂੰ ਇਸ ਨੂੰ ਤੁਹਾਡੀ ਕੁੱਲ ਆਰਡਰ ਸੂਚੀ ਤੋਂ ਹਟਾ ਦੇਣਾ ਚਾਹੀਦਾ ਹੈ ਜਾਂ ਸਭ ਕੁਝ ਹਟਾਉਣ ਲਈ ਸਭ ਸਾਫ਼ ਕਰਨਾ ਚਾਹੀਦਾ ਹੈ. ",
    "HELPTOTALORDERSwWINDOWS10":  "ਕਿਰਪਾ ਕਰਕੇ ਆਪਣੇ ਆਰਡਰ ਨੂੰ ਸਕੈਨ ਕਰੋ ਅਤੇ ਜੇ ਕੋਈ ਅਜਿਹੀ ਚੀਜ਼ ਹੈ ਜਿਸਦੀ ਤੁਸੀਂ ਆਰਡਰ ਨਹੀਂ ਕਰਨਾ ਚਾਹੁੰਦੇ ਤਾਂ ਉਸ ਆਈਟਮ ਤੇ ਸਿਰਫ ਸੱਜਾ ਕਲਿਕ ਕਰੋ ਅਤੇ ਮਿਟਾਉਣ ਲਈ ਵਿਕਲਪ ਦੀ ਚੋਣ ਕਰੋ ਅਤੇ ਇਸਨੂੰ ਤੁਹਾਡੀ ਕੁੱਲ ਆਰਡਰ ਸੂਚੀ ਵਿੱਚੋਂ ਹਟਾ ਦੇਣਾ ਚਾਹੀਦਾ ਹੈ. ",
    "HELPUSERPROFILE":  "ਇਹ ਉਹ ਉਪਭੋਗਤਾ ਪ੍ਰੋਫਾਈਲ ਹੈ ਜਿਸਦੀ ਵਰਤੋਂ ਤੁਹਾਨੂੰ ਡਿਜੀਟਲ ਸ਼ਾਪ ਉਦਯੋਗਪਤੀ ਤੁਹਾਨੂੰ ਲੱਭਣ ਲਈ ਕਰੇਗੀ. ",
    "HELPUSERREGISTER":  "ਆਪਣਾ ਪਹਿਲਾ ਨਾਮ, ਆਖਰੀ ਨਾਮ ਅਤੇ ਈਮੇਲ ਪਤਾ ਦਾਖਲ ਕਰੋ ਜਿਸ ਨਾਲ ਅਸੀਂ ਤੁਹਾਨੂੰ ਇੱਕ ਐਕਟਿਵੇਸ਼ਨ ਈਮੇਲ ਭੇਜਾਂਗੇ ਜਿਸ ਤੋਂ ਪਹਿਲਾਂ ਕਿ ਤੁਸੀਂ ਡਿਜੀਟਲ ਸ਼ਾਪ ਵਿੱਚ ਦਾਖਲ ਹੋ ਸਕੋ. ",
    "Hindi":  "ਹਿੰਦੀ",
    "Home":  "ਘਰ",
    "HomeIcon":  "ਹੋਮ ਆਈਕਨ",
    "Hungarian":  "ਹੰਗਰੀਅਨ",
    "Hybrid":  "ਹਾਈਬ੍ਰਿਡ",
    "HybridView":  "ਹਾਈਬ੍ਰਿਡ ਦ੍ਰਿਸ਼",
    "Icelandic":  "ਆਈਸਲੈਂਡਿਕ",
    "Irish":  "ਆਇਰਿਸ਼",
    "isnowClosed":  "ਹੁਣ ਬੰਦ ਹੈ",
    "isusingtheDigitalShopApp":  "ਡਿਜੀਟਲ ਸ਼ਾਪ ਐਪ ਦੀ ਵਰਤੋਂ ਕਰ ਰਿਹਾ ਹੈ",
    "Italy":  "ਇਟਲੀ",
    "ItemAddedtoBasket":  "ਆਈਟਮ ਬਾਸਕੇਟ ਵਿੱਚ ਸ਼ਾਮਲ ਕੀਤੀ ਗਈ",
    "ItemDescription":  "ਆਈਟਮ ਵੇਰਵਾ",
    "ItemName":  "ਆਈਟਮ ਦਾ ਨਾਮ",
    "Japanese":  "ਜਪਾਨੀ",
    "Korean":  "ਕੋਰੀਅਨ",
    "LadiesClotghingIcon":  "ਲੇਡੀਜ਼ ਕਲੌਥਿੰਗ ਆਈਕਨ",
    "LastName":  "ਆਖੀਰਲਾ ਨਾਂਮ",
    "ListView":  "ਸੂਚੀ ਦ੍ਰਿਸ਼",
    "LiveOrderDescription":  "ਡਿਜੀਟਲ ਸ਼ਾਪ ਉਦਯੋਗਪਤੀ ਨੂੰ ਹੁਣ ਆਰਡਰ ਦੇ ਭਾਗ ਵੇਖਣੇ ਚਾਹੀਦੇ ਹਨ ਜਿਸ ਦੀ ਉਨ੍ਹਾਂ ਨੂੰ ਡਿਜੀਟਲ ਦੁਕਾਨ ਦੇ ਗਾਹਕ ਨੂੰ ਭਰਨ ਦੀ ਜ਼ਰੂਰਤ ਹੈ.",
    "LiveOrdersPageTitle":  "ਆਰਡਰ ਸੂਚੀ",
    "LocationDenied":  "ਸਥਾਨ ਅਸਵੀਕਾਰ ਕੀਤਾ",
    "LoginFailedyouhave":  "ਲੌਗਇਨ ਅਸਫਲ, ਤੁਹਾਡੇ ਕੋਲ ਹੈ",
    "Male":  "ਨਰ",
    "Maps":  "ਨਕਸ਼ੇ",
    "MapView":  "ਨਕਸ਼ਾ ਦ੍ਰਿਸ਼",
    "MaxGroupsReached":  "ਵੱਧ ਤੋਂ ਵੱਧ ਸਮੂਹ ਪਹੁੰਚ ਗਏ, ਕਿਰਪਾ ਕਰਕੇ ਅਦਾਇਗੀ ਵਾਲੇ ਸੰਸਕਰਣ ਵਿੱਚ ਅਪਗ੍ਰੇਡ ਕਰਨ ਬਾਰੇ ਵਿਚਾਰ ਕਰੋ",
    "MaxItemsReached":  "ਜੋੜੀਆਂ ਗਈਆਂ ਅਧਿਕਤਮ ਆਈਟਮਾਂ ਪਹੁੰਚੀਆਂ, ਜਦੋਂ ਉਪਲਬਧ ਹੋਣ ਤਾਂ ਭੁਗਤਾਨ ਕੀਤੇ ਸੰਸਕਰਣ ਵਿੱਚ ਅਪਗ੍ਰੇਡ ਕਰਨ ਬਾਰੇ ਵਿਚਾਰ ਕਰੋ",
    "MensClothingIcon":  "ਮੈਨ ਕਪੜੇ ਆਈਕਾਨ",
    "MessageUsersEmailOrPassword":  "ਉਸ ਈਮੇਲ ਜਾਂ ਪਾਸਵਰਡ ਵਾਲਾ ਉਪਭੋਗਤਾ ਮੌਜੂਦ ਨਹੀਂ ਹੈ!",
    "MHELPMAPMANYPAID":  "ਇਹ ਨਕਸ਼ਾ ਤੁਹਾਨੂੰ ਕਿਸੇ ਵੀ ਅਦਾਇਗੀ ਡਿਜੀਟਲ ਦੁਕਾਨਾਂ ਨੂੰ ਦਿਖਾਏਗਾ ਜੋ ਤੁਹਾਡੇ ਮੌਜੂਦਾ ਖੇਤਰ ਵਿੱਚ ਬਣਾਇਆ ਗਿਆ ਹੈ. ",
    "Mobile":  "ਮੋਬਾਈਲ ਨੰਬਰ",
    "MobileIcon":  "ਮੋਬਾਈਲ ਆਈਕਾਨ",
    "Month":  "ਮਹੀਨਾ",
    "moreattempsbeforetheAccountislocked":  "ਅਕਾਉਂਟ ਨੂੰ ਲਾਕ ਕਰਨ ਤੋਂ ਪਹਿਲਾਂ ਹੋਰ ਕੋਸ਼ਿਸ਼ਾਂ",
    "Name":  "ਨਾਮ",
    "Needlocation":  "ਸਥਾਨ ਚਾਹੀਦਾ ਹੈ",
    "NeedStorage":  "ਸਟੋਰੇਜ ਚਾਹੀਦਾ ਹੈ",
    "Noitemsforsale":  "ਵਿਕਰੀ ਲਈ ਕੋਈ ਵਸਤੂਆਂ ਨਹੀਂ",
    "NoNotifications":  "ਕੋਈ ਸੂਚਨਾਵਾਂ ਨਹੀਂ",
    "NoOrdersToshow":  "ਦਿਖਾਉਣ ਲਈ ਕੋਈ ਆਦੇਸ਼ ਨਹੀਂ",
    "Noshopinyourarea":  "ਤੁਹਾਡੇ ਖੇਤਰ ਵਿੱਚ ਕੋਈ ਦੁਕਾਨਾਂ ਨਹੀਂ ਹਨ",
    "NotDelivered":  "ਨਹੀਂ ਦਿੱਤਾ ਗਿਆ",
    "NotPaid":  "ਭੁਗਤਾਨ ਨਹੀਂ ਕੀਤਾ ਗਿਆ",
    "OK":  "ਠੀਕ ਹੈ",
    "Onethousand":  "1000",
    "OnlyPromemberscanupdateGPS":  "ਸਿਰਫ ਪ੍ਰੋ ਮੈਂਬਰ ਜੀਪੀਐਸ ਨੂੰ ਅਪਡੇਟ ਕਰ ਸਕਦੇ ਹਨ",
    "OnSite":  "ਸਾਈਟ ਤੇ",
    "OpeningTimes":  "ਖੁੱਲ੍ਹਣ ਦਾ ਸਮਾਂ",
    "Order":  "ਆਰਡਰ",
    "Orders":  "ਆਰਡਰ",
    "Ordersoftheday":  "ਦਿਨ ਦੇ ਆਰਡਰ",
    "Ordersofthemonth":  "ਮਹੀਨੇ ਦੇ ਆਰਡਰ",
    "Ordersoftheweekand":  "ਹਫ਼ਤੇ ਦੇ ਆਰਡਰ ਅਤੇ",
    "Paid":  "ਦਾ ਭੁਗਤਾਨ",
    "PaidView":  "ਅਦਾਇਗੀ ਦੁਕਾਨਾਂ ਵੇਖੋ",
    "Password":  "ਪਾਸਵਰਡ",
    "PasswordReset":  "ਪਾਸਵਰਡ ਰੀਸੈਟ ਕਰੋ, ਕਿਰਪਾ ਕਰਕੇ ਆਪਣੀ ਈਮੇਲ ਵੇਖੋ",
    "PaymentStatus":  "ਭੁਗਤਾਨ ਦੀ ਸਥਿਤੀ",
    "PayOnPhoneareEnabled":  "ਫੋਨ \u0027ਤੇ ਭੁਗਤਾਨ ਯੋਗ ਹੈ",
    "PermissionsDenied":  "ਅਧਿਕਾਰ ਅਸਵੀਕਾਰ ਕੀਤੇ ਗਏ",
    "PickerNotifications":  "ਨੋਟੀਫਿਕੇਸ਼ਨ",
    "Pleasecheckyourinternetconnection":  "ਕਿਰਪਾ ਕਰਕੇ ਆਪਣੇ ਇੰਟਰਨੈਟ ਕਨੈਕਸ਼ਨ ਦੀ ਜਾਂਚ ਕਰੋ",
    "PleaseconsiderupgradingtopaidversiontomakeyourDigitalShopGlobal":  "ਕਿਰਪਾ ਕਰਕੇ ਆਪਣੀ DigitalShop ਨੂੰ ਗਲੋਬਲ ਬਣਾਉਣ ਲਈ ਭੁਗਤਾਨ ਕੀਤੇ ਸੰਸਕਰਣ \u0027ਤੇ ਅੱਪਗ੍ਰੇਡ ਕਰਨ ਬਾਰੇ ਵਿਚਾਰ ਕਰੋ",
    "Pleasecreateacompanyfirst":  "ਕਿਰਪਾ ਕਰਕੇ ਪਹਿਲਾਂ ਇੱਕ ਕੰਪਨੀ ਬਣਾਓ",
    "Pleasedelete":  "ਕਿਰਪਾ ਕਰਕੇ ਮਿਟਾਓ",
    "PleasedeleteSubMenuItemsBeforeyoucandeletetheMainGroup":  "ਮੇਨ ਗਰੁੱਪ ਨੂੰ ਮਿਟਾਉਣ ਤੋਂ ਪਹਿਲਾਂ ਕਿਰਪਾ ਕਰਕੇ ਸਬਮੈਨੂ ਆਈਟਮਾਂ ਨੂੰ ਮਿਟਾਓ",
    "PleaseselectLanguage":  "ਕਿਰਪਾ ਕਰਕੇ ਭਾਸ਼ਾ ਦੀ ਚੋਣ ਕਰੋ",
    "Pleasewait":  "ਕ੍ਰਿਪਾ ਕਰਕੇ ਉਡੀਕ ਕਰੋ...",
    "Polish":  "ਪੋਲਿਸ਼",
    "Portuguese":  "ਪੁਰਤਗਾਲੀ",
    "Price":  "ਮੁੱਲ",
    "PrivateKeyCanNotbeEmpty":  "ਨਿਜੀ ਕੁੰਜੀ ਖਾਲੀ ਨਹੀਂ ਹੋ ਸਕਦੀ",
    "PubIcon":  "ਪਬ ਆਈਕਨ",
    "PublicKeyCanNotbeEmpty":  "ਪਬਲਿਕ ਕੁੰਜੀ ਖਾਲੀ ਨਹੀਂ ਹੋ ਸਕਦੀ",
    "Punjabi":  "ਪੰਜਾਬੀ",
    "Purchasewasemptrypleasetryagain":  "ਖਰੀਦ ਖਾਲੀ ਸੀ, ਦੁਬਾਰਾ ਕੋਸ਼ਿਸ਼ ਕਰੋ",
    "PurchasewasSuccessfull":  "ਖਰੀਦ ਸਫਲਤਾਪੂਰਵਕ ਸੀ",
    "ReddishBackGround":  "ਲਾਲ",
    "Register":  "ਰਜਿਸਟਰ",
    "RegistrationFailed":  "ਰਜਿਸਟ੍ਰੇਸ਼ਨ ਅਸਫਲ",
    "RegistrationFailedAgecannotbeempty":  "ਰਜਿਸਟ੍ਰੇਸ਼ਨ ਅਸਫਲ, ਉਮਰ ਖਾਲੀ ਨਹੀਂ ਹੋ ਸਕਦੀ",
    "RegistrationFailedCompanyEmailscannotbeempty":  "ਰਜਿਸਟ੍ਰੇਸ਼ਨ ਅਸਫਲ ਕੰਪਨੀ ਦੀ ਈਮੇਲ ਖਾਲੀ ਨਹੀਂ ਹੋ ਸਕਦੀ",
    "RegistrationFailedCompanyNamecannotbeempty":  "ਰਜਿਸਟ੍ਰੇਸ਼ਨ ਅਸਫਲ ਕੰਪਨੀ ਦਾ ਨਾਮ ਖਾਲੀ ਨਹੀਂ ਹੋ ਸਕਦਾ",
    "RegistrationFailedContactNumbercannotbeempty":  "ਰਜਿਸਟ੍ਰੇਸ਼ਨ ਅਸਫਲ, ਸੰਪਰਕ ਨੰਬਰ ਖਾਲੀ ਨਹੀਂ ਹੋ ਸਕਦਾ",
    "RegistrationFailedEmailaddesscannotbeempty":  "ਰਜਿਸਟ੍ਰੇਸ਼ਨ ਅਸਫਲ, ਈਮੇਲ ਪਤਾ ਖਾਲੀ ਨਹੀਂ ਹੋ ਸਕਦਾ",
    "RegistrationFailedEmailaddessneedstocontainatsymbol":  "ਰਜਿਸਟ੍ਰੇਸ਼ਨ ਅਸਫਲ ਈਮੇਲ ਐਡਰੈੱਸ ਨੂੰ @ ਚਿੰਨ੍ਹ ਹੋਣ ਦੀ ਜ਼ਰੂਰਤ ਹੈ",
    "RegistrationFailedFirstNamecannotbeempty":  "ਰਜਿਸਟ੍ਰੇਸ਼ਨ ਅਸਫਲ, ਪਹਿਲਾ ਨਾਮ ਖਾਲੀ ਨਹੀਂ ਹੋ ਸਕਦਾ",
    "RegistrationFailedGendercannotbeempty":  "ਰਜਿਸਟ੍ਰੇਸ਼ਨ ਅਸਫਲ ਲਿੰਗ ਖਾਲੀ ਨਹੀਂ ਹੋ ਸਕਦਾ",
    "RegistrationFailedGPSLatcannotbeempty":  "ਰਜਿਸਟ੍ਰੇਸ਼ਨ ਅਸਫਲ GPS ਲੈਟ ਖਾਲੀ ਨਹੀਂ ਹੋ ਸਕਦਾ",
    "RegistrationFailedGPSLongcannotbeempty":  "ਰਜਿਸਟ੍ਰੇਸ਼ਨ ਅਸਫਲ ਜੀਪੀਐਸ ਲੋਂਗ ਖਾਲੀ ਨਹੀਂ ਹੋ ਸਕਦੀ",
    "RegistrationFailedLastNamecannotbeempty":  "ਰਜਿਸਟ੍ਰੇਸ਼ਨ ਅਸਫਲ, ਆਖਰੀ ਨਾਮ ਖਾਲੀ ਨਹੀਂ ਹੋ ਸਕਦਾ",
    "RegistrationFailedPasswordcannotbeempty":  "ਰਜਿਸਟ੍ਰੇਸ਼ਨ ਅਸਫਲ, ਪਾਸਵਰਡ ਖਾਲੀ ਨਹੀਂ ਹੋ ਸਕਦਾ",
    "RegistrationFailedPasswordcannotbeLessThan7":  "ਰਜਿਸਟ੍ਰੇਸ਼ਨ ਅਸਫਲ ਪਾਸਵਰਡ ਲੰਬਾਈ ਦੇ 7 ਪਾਠਕਾਂ ਤੋਂ ਘੱਟ ਨਹੀਂ ਹੋ ਸਕਦਾ",
    "RegistrationLinkClicked":  "ਤੁਹਾਡੇ ਈਮੇਲ ਖਾਤੇ ਦੀ ਪੁਸ਼ਟੀ ਕਰਨ ਲਈ ਅਸੀਂ ਤੁਹਾਨੂੰ ਈਮੇਲ ਰਾਹੀਂ ਇੱਕ ਲਿੰਕ ਭੇਜਿਆ ਹੈ, ਕਿਰਪਾ ਕਰਕੇ ਕਲਿੱਕ ਕਰੋ ਅਤੇ ਫਿਰ ਐਂਟਰ ਟੂ ਡਿਜੀਟਲ ਸ਼ਾਪ ਤੇ ਵਾਪਸ ਜਾਓ",
    "RegistrationSuccessful":  "ਰਜਿਸਟ੍ਰੇਸ਼ਨ ਸਫਲ",
    "RequestCancel":  "ਬੇਨਤੀ ਰੱਦ ਕਰੋ",
    "REQUESTTOCANCEL":  "ਰੱਦ ਕਰਨ ਲਈ ਬੇਨਤੀ",
    "Requestwassent":  "ਬੇਨਤੀ ਭੇਜੀ ਗਈ",
    "ResetLoginPassword":  "ਲੌਗਇਨ ਪਾਸਵਰਡ ਰੀਸੈਟ ਕਰੋ",
    "RestaurantIcon":  "ਰੈਸਟੋਰੈਂਟ ਆਈਕਾਨ",
    "Romanian":  "ਰੋਮਾਨੀਅਨ",
    "Russian":  "ਰੂਸੀ",
    "SandwichesIcon":  "ਸੈਂਡਵਿਚ ਆਈਕਾਨ",
    "Satellite":  "ਸੈਟੇਲਾਈਟ",
    "Save":  "ਸੇਵ",
    "SaveFailed":  "ਸੇਵ ਅਸਫਲ",
    "SaveKeys":  "ਕੁੰਜੀਆਂ ਸੰਭਾਲੋ",
    "SaveSuccessful":  "ਸਫਲਤਾਪੂਰਵਕ ਸੰਭਾਲੋ",
    "Scan":  "ਕਿ Qਆਰ ਕੋਡ ਸਕੈਨਰ",
    "Scottish":  "ਸਕੌਟਿਸ਼",
    "SelectLanguage":  "ਭਾਸ਼ਾ ਚੁਣੋ",
    "SelectTheme":  "ਥੀਮ ਚੁਣੋ",
    "Share":  "ਸਾਂਝਾ ਕਰੋ",
    "ShopActivity":  "ਦੁਕਾਨ ਦੀ ਗਤੀਵਿਧੀ",
    "ShopIcon":  "ਸ਼ਾਪ ਆਈਕਾਨ",
    "Signin":  "ਸਾਈਨ - ਇਨ",
    "sms":  "ਐਸ.ਐਮ.ਐੱਸ",
    "Spanish":  "ਸਪੈਨਿਸ਼",
    "Storage":  "ਸਟੋਰੇਜ",
    "Street":  "ਗਲੀ",
    "StripePrivateKey":  "ਪ੍ਰਾਈਵੇਟ ਕੁੰਜੀ",
    "StripePublicKey":  "ਪਬਲਿਕ ਕੁੰਜੀ",
    "Swedish":  "ਸਵੀਡਿਸ਼",
    "TableNumber":  "ਟੇਬਲ ਨੰਬਰ",
    "TakeAway":  "ਲੈ ਜਾਓ",
    "TakewaysisEnabled":  "ਟੇਕਵੇਅ ਯੋਗ ਹੈ",
    "Thailand":  "ਥਾਈਲੈਂਡ",
    "TheItemisEnabled":  "ਆਈਟਮ ਯੋਗ ਹੈ",
    "Therewasanerror":  "ਇੱਕ ਗਲਤੀ ਹੋਈ ਹੈ ਕਿਰਪਾ ਕਰਕੇ Support@TechGuyGeek.com ਤੇ ਸੰਪਰਕ ਕਰੋ",
    "ThishasnotbeenimplenetedyetPleaseemailformoreinformation":  "ਇਹ ਅਜੇ ਤੱਕ ਲਾਗੂ ਨਹੀਂ ਕੀਤਾ ਗਿਆ ਹੈ, ਕਿਰਪਾ ਕਰਕੇ ਵਧੇਰੇ ਜਾਣਕਾਰੀ ਲਈ ਈਮੇਲ ਕਰੋ",
    "Today":  "ਅੱਜ",
    "Total":  "ਕੁੱਲ",
    "Totalitems":  "ਕੁੱਲ ਇਕਾਈਆਂ",
    "TOTALPRICE":  "ਕੁੱਲ ਕੀਮਤ",
    "ToysIcon":  "ਖਿਡੌਣੇ ਆਈਕਾਨ",
    "Turkish":  "ਤੁਰਕੀ",
    "Ukrainian":  "ਯੂਕਰੇਨੀਅਨ",
    "Unabletotakephotos":  "ਫੋਟੋਆਂ ਲੈਣ ਵਿੱਚ ਅਸਮਰੱਥ.",
    "UpdatecompanyGPS":  "ਕੰਪਨੀ ਜੀਪੀਐਸ ਨੂੰ ਅਪਡੇਟ ਕਰੋ",
    "UpdateGPS":  "ਜੀਪੀਐਸ ਅਪਡੇਟ ਕਰੋ",
    "Usernameorpasswordcannotbeempty":  "ਉਪਭੋਗਤਾ ਨਾਮ ਜਾਂ ਪਾਸਵਰਡ ਖਾਲੀ ਨਹੀਂ ਹੋ ਸਕਦਾ",
    "UserOrderDetails":  "ਉਪਭੋਗਤਾ ਉਨ੍ਹਾਂ ਸਾਰੇ ਉਤਪਾਦਾਂ ਦਾ ਪੂਰਾ ਵੇਰਵਾ ਦੇਖ ਸਕਦਾ ਹੈ ਜੋ ਉਨ੍ਹਾਂ ਨੇ ਮੌਜੂਦਾ ਚੁਣੇ ਹੋਏ ਆਰਡਰ ਨਾਲ ਆਰਡਰ ਕੀਤੇ ਹਨ, ਕਿਰਪਾ ਕਰਕੇ ਜਾਰੀ ਰੱਖਣ ਲਈ ਵਾਪਸ ਕਲਿੱਕ ਕਰੋ",
    "UserProfile":  "ਉਪਭੋਗਤਾ ਪ੍ਰੋਫਾਈਲ",
    "UserProfilePageTitle":  "ਯੂਜ਼ਰ ਪਰੋਫਾਈਲ ਸੋਧੋ",
    "Userwiththatemaildoesntexist":  "ਉਸ ਈਮੇਲ ਵਾਲਾ ਉਪਭੋਗਤਾ ਮੌਜੂਦ ਨਹੀਂ ਹੈ!",
    "Usingthe":  "ਦੀ ਵਰਤੋਂ",
    "ViewGlobalShops":  "ਗਲੋਬਲ ਦੁਕਾਨਾਂ ਦੇਖੋ",
    "ViewOrders":  "ਆਰਡਰ ਵੇਖੋ",
    "ViewShops":  "ਦੁਕਾਨਾਂ ਵੇਖੋ",
    "Wasnotdeleted":  "ਹਟਾਇਆ ਨਹੀਂ ਗਿਆ ਸੀ",
    "Week":  "ਹਫ਼ਤਾ",
    "Welsh":  "ਵੈਲਸ਼",
    "WhiteBackGround":  "ਰੋਸ਼ਨੀ",
    "Youcannotdeleteasyouhave":  "ਤੁਸੀਂ ਹਟਾ ਨਹੀਂ ਸਕਦੇ ਜਿਵੇਂ ਤੁਹਾਡੇ ਕੋਲ ਹੈ",
    "YouhavenoOrders":  "ਤੁਹਾਡੇ ਕੋਲ ਕੋਈ ਆਰਡਰ ਨਹੀਂ ਹਨ",
    "YouhaveNoOrdersselected":  "ਤੁਹਾਡੇ ਕੋਲ ਕੋਈ ਆਰਡਰ ਨਹੀਂ ਚੁਣਿਆ ਗਿਆ ਹੈ",
    "yourcompanyfirst":  "ਤੁਹਾਡੀ ਕੰਪਨੀ ਪਹਿਲਾਂ",
    "YourcurrentGPSisnegative":  "ਤੁਹਾਡਾ ਮੌਜੂਦਾ ਜੀਪੀਐਸ ਨਾਕਾਰਾਤਮਕ ਹੈ ਕਿਰਪਾ ਕਰਕੇ ਲੌਗ ਆਉਟ ਕਰੋ ਅਤੇ ਵਾਪਸ ਆਓ ਜਾਂ ਆਪਣਾ ਮੌਜੂਦਾ ਇੰਟਰਨੈਟ ਕਨੈਕਸ਼ਨ ਬਦਲੋ",
    "YourLivetorecieveOrders":  "ਆਰਡਰ ਪ੍ਰਾਪਤ ਕਰਨ ਲਈ ਤੁਹਾਡਾ ਲਾਈਵ",
    "Zero":  "0",
    "ChooseMapMarker":  "ਨਕਸ਼ਾ ਮਾਰਕਰ ਚੁਣੋ"
}